planetoidAI/__init__.py
planetoidAI-0.0.2.dist-info/LICENSE
planetoidAI-0.0.2.dist-info/METADATA
planetoidAI-0.0.2.dist-info/WHEEL
planetoidAI-0.0.2.dist-info/top_level.txt
planetoidAI-0.0.2.dist-info/RECORD
