Metadata-Version: 2.1
Name: planetoidAI
Version: 0.0.2
Summary: Planetoid's official library to access free API
Home-page: https://github.com/HimanshuMoliya/planetoid.git
Author: Himanshu Moliya (Founder)
License: MIT
Download-URL: https://pypi.org/project/planetoidAI/0.0.1/
Project-URL: Bug Tracker, https://github.com/HimanshuMoliya/planetoid/issues
Keywords: pypi,planetoid,planetoid-api,free,api,himanshumoliya,himanshu
Platform: UNKNOWN
License-File: LICENSE
Requires-Dist: requests
